msglib/__init__.py
msglib/broker.py
msglib/client.py
msglib/handlers.py
msglib/ios/__init__.py
msglib/ios/io_memory.py
msglib/ios/io_sockets.py
msglib/message.py
msglib-0.2.0.dist-info/LICENSE
msglib-0.2.0.dist-info/METADATA
msglib-0.2.0.dist-info/WHEEL
msglib-0.2.0.dist-info/RECORD
